LICENSE
MANIFEST.in
README.rst
setup.py
tellcorenet.py
tellcore_net.egg-info/PKG-INFO
tellcore_net.egg-info/SOURCES.txt
tellcore_net.egg-info/dependency_links.txt
tellcore_net.egg-info/not-zip-safe
tellcore_net.egg-info/top_level.txt